[{"__type__":"cc.SpriteFrame","content":{"name":"back icon","texture":"aejj1gdn5JO4pNa1ZOfsqw","rect":[0,0,24,24],"offset":[0,0],"originalSize":[24,24],"capInsets":[0,0,0,0]}},{"__type__":"cc.SpriteFrame","content":{"name":"singleColor","texture":"1bags8Kg5BCpWrU9yaA6Ng","rect":[0,0,2,2],"offset":[0,0],"originalSize":[2,2],"capInsets":[0,0,0,0]}},[{"__type__":"cc.Prefab","_name":"ListItem","data":{"__id__":1}},{"__type__":"cc.Node","_name":"item","_children":[{"__id__":2}],"_components":[{"__type__":"aa63bWNE8hBf4P4Sp0X2uT0","node":{"__id__":1},"label":{"__id__":3},"bg":{"__id__":4},"btn":{"__id__":5}},{"__id__":4},{"__id__":5}],"_prefab":{"__type__":"cc.PrefabInfo","root":{"__id__":1},"asset":{"__uuid__":"1eoho0ymhIgI32BauxkHn9"},"fileId":"7838dEuCdBIjomA/4pnvg05"},"_contentSize":{"__type__":"cc.Size","width":400,"height":40},"_anchorPoint":{"__type__":"cc.Vec2","y":0.5},"_trs":{"__type__":"TypedArray","ctor":"Float64Array","array":[50,-50,0,0,0,0,0,1,1,1]}},{"__type__":"cc.Node","_name":"label","_parent":{"__id__":1},"_components":[{"__type__":"cc.Widget","node":{"__id__":2},"alignMode":0,"_alignFlags":45,"_left":30,"_right":285.51,"_top":4.25,"_bottom":4.25,"_originalWidth":482,"_originalHeight":33},{"__id__":3}],"_prefab":{"__type__":"cc.PrefabInfo","root":{"__id__":1},"asset":{"__uuid__":"1eoho0ymhIgI32BauxkHn9"},"fileId":"a552bVxCCBNdLO5TgH0HsGm"},"_color":{"__type__":"cc.Color"},"_contentSize":{"__type__":"cc.Size","width":84.49,"height":31.5},"_anchorPoint":{"__type__":"cc.Vec2","y":0.5},"_trs":{"__type__":"TypedArray","ctor":"Float64Array","array":[30,0,0,0,0,0,0,1,1,1]}},{"__type__":"cc.Label","node":{"__id__":2},"_useOriginalSize":false,"_string":"Label sss","_N$string":"Label sss","_fontSize":20,"_lineHeight":25,"_N$verticalAlign":1},{"__type__":"cc.Sprite","node":{"__id__":1},"_spriteFrame":{"__uuid__":"93IPCkVxlHqI9nYkpyw1bw"},"_type":1,"_sizeMode":0},{"__type__":"cc.Button","node":{"__id__":1},"clickEvents":[{"__type__":"cc.ClickEvent","target":{"__id__":1},"_componentId":"aa63bWNE8hBf4P4Sp0X2uT0","handler":"loadExample"}],"_N$transition":1,"transition":1,"_N$pressedColor":{"__type__":"cc.Color","r":192,"g":191,"b":191},"pressedColor":{"__type__":"cc.Color","r":192,"g":191,"b":191},"_N$hoverColor":{"__type__":"cc.Color","r":180,"g":180,"b":180},"hoverColor":{"__type__":"cc.Color","r":180,"g":180,"b":180},"_N$disabledColor":{"__type__":"cc.Color","r":255,"g":255,"b":255},"_N$target":{"__id__":1}}],{"__type__":"cc.SpriteFrame","content":{"name":"next_scene","texture":"a9HkOPOMNMyZ+GMTiyr9r6","rect":[0,0,24,24],"offset":[0,0],"originalSize":[24,24],"capInsets":[0,0,0,0]}},[{"__type__":"cc.Prefab","_name":"Left Menu","data":{"__id__":1}},{"__type__":"cc.Node","_name":"Left Menu","_children":[{"__id__":2}],"_components":[{"__type__":"cc.Widget","node":{"__id__":1},"_alignFlags":9,"_left":-23,"_top":-23}],"_prefab":{"__type__":"cc.PrefabInfo","root":{"__id__":1},"asset":{"__uuid__":"6ci1CbxR9HcJuwnERKv5yD"},"fileId":"f1ydjOcixPCqfRy24wZSRW"},"_trs":{"__type__":"TypedArray","ctor":"Float64Array","array":[-480,320,0,0,0,0,0,1,1,1]},"_zIndex":0},{"__type__":"cc.Node","_name":"btnBack","_parent":{"__id__":1},"_children":[{"__id__":3}],"_components":[{"__type__":"cc.Sprite","node":{"__id__":2},"_spriteFrame":{"__uuid__":"a2MjXRFdtLlYQ5ouAFv/+R"},"_type":1,"_sizeMode":0},{"__type__":"cc.Button","node":{"__id__":2},"clickEvents":[null],"_N$transition":1,"transition":1,"_N$normalColor":{"__type__":"cc.Color","g":171,"b":248},"_N$pressedColor":{"__type__":"cc.Color","g":141,"b":206},"pressedColor":{"__type__":"cc.Color","g":141,"b":206},"_N$hoverColor":{"__type__":"cc.Color","r":60,"g":186,"b":247},"hoverColor":{"__type__":"cc.Color","r":60,"g":186,"b":247},"_N$disabledColor":{"__type__":"cc.Color","r":255,"g":255,"b":255},"_N$target":{"__id__":2}}],"_prefab":{"__type__":"cc.PrefabInfo","root":{"__id__":1},"asset":{"__uuid__":"6ci1CbxR9HcJuwnERKv5yD"},"fileId":"715adW7LO1A/ZA67FJaVh1v"},"_color":{"__type__":"cc.Color","g":171,"b":248},"_contentSize":{"__type__":"cc.Size","width":141,"height":90},"_anchorPoint":{"__type__":"cc.Vec2","x":0.6976691438212628,"y":0.9695517305558904},"_trs":{"__type__":"TypedArray","ctor":"Float64Array","array":[0,0,0,0,0,0,0,1,1,1]},"_eulerAngles":{"__type__":"cc.Vec3","z":45},"_zIndex":0},{"__type__":"cc.Node","_name":"back icon","_parent":{"__id__":2},"_components":[{"__type__":"cc.Sprite","node":{"__id__":3},"_srcBlendFactor":1,"_spriteFrame":{"__uuid__":"02GjIXRNdDj6if+Hv+vonZ"}}],"_prefab":{"__type__":"cc.PrefabInfo","root":{"__id__":1},"asset":{"__uuid__":"6ci1CbxR9HcJuwnERKv5yD"},"fileId":"8cZw5sGQdLVbn1tTdC1CUt"},"_contentSize":{"__type__":"cc.Size","width":24,"height":24},"_trs":{"__type__":"TypedArray","ctor":"Float64Array","array":[-4.392893314361572,-56.47005844116211,0,0,0,0,0,1.7000000476837158,1.7000000476837158,1]},"_eulerAngles":{"__type__":"cc.Vec3","z":-45},"_zIndex":0}],{"__type__":"cc.SpriteFrame","content":{"name":"panelBG","texture":"32Kf6rsGJMda2RuWJgLe8h","rect":[0,0,27,30],"offset":[0,0],"originalSize":[27,30],"capInsets":[11,12,11,15]}},[{"__type__":"cc.Prefab","_name":"Center Menu","data":{"__id__":1}},{"__type__":"cc.Node","_name":"Center Menu","_children":[{"__id__":2},{"__id__":3}],"_components":[{"__type__":"cc.Widget","node":{"__id__":1},"_alignFlags":20,"_bottom":-6,"_horizontalCenter":18}],"_prefab":{"__type__":"cc.PrefabInfo","root":{"__id__":1},"asset":{"__uuid__":"98Geqpg5RDwrIsjuR985Yq"},"fileId":"612uCk0ntIFZeVwJb0ciY5"},"_trs":{"__type__":"TypedArray","ctor":"Float64Array","array":[18,-303,0,0,0,0,0,1.2999999523162842,1.2999999523162842,1]},"_zIndex":0},{"__type__":"cc.Node","_name":"next_scene","_parent":{"__id__":1},"_components":[{"__type__":"cc.Sprite","node":{"__id__":2},"_srcBlendFactor":1,"_spriteFrame":{"__uuid__":"28tsJhakVPrYWSz2g4Kmv5"}},{"__type__":"cc.Button","node":{"__id__":2},"clickEvents":[null],"_N$transition":1,"transition":1,"_N$normalColor":{"__type__":"cc.Color","r":214,"g":214,"b":214},"_N$target":{"__id__":2}}],"_prefab":{"__type__":"cc.PrefabInfo","root":{"__id__":1},"asset":{"__uuid__":"98Geqpg5RDwrIsjuR985Yq"},"fileId":"79eAfRmbxE6qvp2/Qe1g2B"},"_color":{"__type__":"cc.Color","r":214,"g":214,"b":214},"_contentSize":{"__type__":"cc.Size","width":24,"height":24},"_trs":{"__type__":"TypedArray","ctor":"Float64Array","array":[325,230,0,0,0,0,0,1.7000000476837158,1.7000000476837158,1]},"_zIndex":0},{"__type__":"cc.Node","_name":"prev_scene","_parent":{"__id__":1},"_components":[{"__type__":"cc.Sprite","node":{"__id__":3},"_srcBlendFactor":1,"_spriteFrame":{"__uuid__":"f1pAvsFlJJtpAm0alGZ09+"}},{"__type__":"cc.Button","node":{"__id__":3},"clickEvents":[null],"_N$transition":1,"transition":1,"_N$normalColor":{"__type__":"cc.Color","r":214,"g":214,"b":214},"_N$target":{"__id__":3}}],"_prefab":{"__type__":"cc.PrefabInfo","root":{"__id__":1},"asset":{"__uuid__":"98Geqpg5RDwrIsjuR985Yq"},"fileId":"60cjAvPQ9D15qIiwkFiCOS"},"_color":{"__type__":"cc.Color","r":214,"g":214,"b":214},"_contentSize":{"__type__":"cc.Size","width":24,"height":24},"_trs":{"__type__":"TypedArray","ctor":"Float64Array","array":[-355,230,0,0,0,0,0,1.7000000476837158,1.7000000476837158,1]},"_zIndex":0}],{"__type__":"cc.SpriteFrame","content":{"name":"default_sprite_splash","texture":"02delMVqdBD70a/HSD99FK","rect":[0,0,2,2],"offset":[0,0],"originalSize":[2,2],"capInsets":[0,0,0,0]}},[{"__type__":"cc.Prefab","_name":"Background","data":{"__id__":1},"optimizationPolicy":1},{"__type__":"cc.Node","_name":"Background","_components":[{"__type__":"cc.Sprite","node":{"__id__":1},"_spriteFrame":{"__uuid__":"0aoLNsxKlM4qs77+3nCObU"},"_sizeMode":0},{"__type__":"cc.Widget","node":{"__id__":1},"alignMode":2,"_alignFlags":45,"_originalWidth":960,"_originalHeight":640}],"_prefab":{"__type__":"cc.PrefabInfo","root":{"__id__":1},"asset":{"__uuid__":"b8OSNRvpdPAZhePn0hGPPJ"},"fileId":"78fd70+ls5GgJcFkzvLSRk8"},"_color":{"__type__":"cc.Color","r":56,"g":59,"b":65},"_contentSize":{"__type__":"cc.Size","width":960,"height":640},"_trs":{"__type__":"TypedArray","ctor":"Float64Array","array":[0,0,0,0,0,0,0,1,1,1]},"_zIndex":0}],{"__type__":"cc.SpriteFrame","content":{"name":"btn_disabled","texture":"8aYDUe2cxG9LHWbN42pbmt","rect":[0,0,194,68],"offset":[0,0],"originalSize":[194,68],"capInsets":[5,5,5,5]}},[{"__type__":"cc.SceneAsset","_name":"TestList","scene":{"__id__":1},"asyncLoadAssets":null},{"__type__":"cc.Scene","_name":"New Node","_children":[{"__id__":2},{"__id__":5},{"__id__":9},{"__id__":22}],"_active":false,"_anchorPoint":{"__type__":"cc.Vec2"},"_trs":{"__type__":"TypedArray","ctor":"Float64Array","array":[0,0,0,0,0,0,1,1,1,1]},"autoReleaseAssets":true},{"__type__":"cc.Node","_name":"Canvas","_parent":{"__id__":1},"_children":[{"__id__":3},{"__id__":4}],"_components":[{"__type__":"cc.Canvas","node":{"__id__":2}},{"__type__":"cc.Widget","node":{"__id__":2},"_alignFlags":45}],"_contentSize":{"__type__":"cc.Size","width":960,"height":640},"_trs":{"__type__":"TypedArray","ctor":"Float64Array","array":[480,320,0,0,0,0,1,1,1,1]},"_id":"090d0OFRNNBL77uJm2aDmFX"},{"__type__":"cc.Node","_name":"Main Camera","_parent":{"__id__":2},"_components":[{"__type__":"cc.Camera","node":{"__id__":3},"_cullingMask":-129,"_clearFlags":7,"_backgroundColor":{"__type__":"cc.Color","r":51,"g":77,"b":120},"_depth":-1,"_nearClip":0.1}],"_trs":{"__type__":"TypedArray","ctor":"Float64Array","array":[0,0,322.1614502078112,0,0,0,1,1,1,1]}},{"__type__":"cc.Node","_parent":{"__id__":2},"_id":"9608cbWFmVIM7m6hasLXYV7","_prefab":{"__type__":"cc.PrefabInfo","root":{"__id__":4},"asset":{"__uuid__":"b8OSNRvpdPAZhePn0hGPPJ"},"fileId":"78fd70+ls5GgJcFkzvLSRk8","sync":true},"_name":"Background","_trs":{"__type__":"TypedArray","ctor":"Float64Array","array":[0,0,0,0,0,0,1,1,1,1]}},{"__type__":"cc.Node","_name":"TestList","_parent":{"__id__":1},"_children":[{"__id__":6}],"_components":[{"__id__":8},{"__type__":"cc.Sprite","node":{"__id__":5},"_materials":[{"__uuid__":"ecpdLyjvZBwrvm+cedCcQy"}],"_spriteFrame":{"__uuid__":"benVLTCGJAAp9ZBs9YA6U9"},"_type":1,"_sizeMode":0},{"__type__":"cc.Widget","node":{"__id__":5},"_alignFlags":21,"_verticalCenter":20,"_originalHeight":600}],"_contentSize":{"__type__":"cc.Size","width":600,"height":640},"_trs":{"__type__":"TypedArray","ctor":"Float64Array","array":[480,320,0,0,0,0,1,1,1,1]},"_id":"07237nJ33ZHw7lFr1dvt/S8"},{"__type__":"cc.Node","_name":"viewport","_parent":{"__id__":5},"_children":[{"__id__":7}],"_components":[{"__type__":"cc.Mask","node":{"__id__":6},"_materials":[{"__uuid__":"ecpdLyjvZBwrvm+cedCcQy"}],"_N$alphaThreshold":1},{"__type__":"cc.Widget","node":{"__id__":6},"_alignFlags":45,"_top":-4.190999999999974,"_bottom":4.190999999999974,"_originalWidth":590,"_originalHeight":590}],"_contentSize":{"__type__":"cc.Size","width":600,"height":640},"_trs":{"__type__":"TypedArray","ctor":"Float64Array","array":[0,4.190999999999974,0,0,0,0,1,1,1,1]}},{"__type__":"cc.Node","_name":"list","_parent":{"__id__":6},"_components":[{"__type__":"473b8wxs55OsJvoxVdYCzTF","node":{"__id__":7},"itemPrefab":{"__uuid__":"1eoho0ymhIgI32BauxkHn9"},"initItemCount":18,"scrollView":{"__id__":8},"bufferZone":350}],"_contentSize":{"__type__":"cc.Size","width":600,"height":900},"_anchorPoint":{"__type__":"cc.Vec2","y":1},"_trs":{"__type__":"TypedArray","ctor":"Float64Array","array":[-300,300,0,0,0,0,1,1,1,1]}},{"__type__":"cc.ScrollView","node":{"__id__":5},"horizontal":false,"brake":0.9,"bounceDuration":0.23,"_N$content":{"__id__":7},"content":{"__id__":7},"_N$horizontalScrollBar":null,"_N$verticalScrollBar":null},{"__type__":"cc.Node","_name":"Menu","_parent":{"__id__":1},"_children":[{"__id__":10},{"__id__":12},{"__id__":14},{"__id__":18}],"_components":[{"__type__":"cc.Widget","node":{"__id__":9},"_alignFlags":45,"_left":23,"_right":23,"_top":23,"_bottom":23},{"__type__":"04525pyYBlN26SWawaUF3dA","node":{"__id__":9},"btnBack":{"__id__":17},"testList":{"__id__":8},"uiCamera":{"__id__":11},"sceneTitle":{"__id__":13},"transitions":{"__id__":21}},{"__type__":"9bf9cWgTmNAapAWiQT08YdJ","node":{"__id__":9}}],"_contentSize":{"__type__":"cc.Size","width":914,"height":594},"_trs":{"__type__":"TypedArray","ctor":"Float64Array","array":[480,320,0,0,0,0,1,1,1,1]},"_groupIndex":7,"groupIndex":7,"_id":"d4145fA6E9OsqhRjr87RQ1U"},{"__type__":"cc.Node","_name":"camera","_parent":{"__id__":9},"_components":[{"__id__":11}],"_trs":{"__type__":"TypedArray","ctor":"Float64Array","array":[0,0,322.1614502078112,0,0,0,1,1,1,1]},"_groupIndex":7,"groupIndex":7},{"__type__":"cc.Camera","node":{"__id__":10},"_cullingMask":128,"_backgroundColor":{"__type__":"cc.Color","r":51,"g":77,"b":120},"_nearClip":0.1},{"__type__":"cc.Node","_name":"Scene Title","_parent":{"__id__":9},"_active":false,"_components":[{"__id__":13},{"__type__":"cc.Widget","node":{"__id__":12},"_alignFlags":20,"_top":-11.600000000000023,"_bottom":-13},{"__type__":"cc.LabelOutline","node":{"__id__":12},"_color":{"__type__":"cc.Color"}}],"_color":{"__type__":"cc.Color","r":160,"g":218,"b":250},"_contentSize":{"__type__":"cc.Size","width":50.94,"height":40},"_trs":{"__type__":"TypedArray","ctor":"Float64Array","array":[0,-290,0,0,0,0,1,1,1,1]},"_groupIndex":7,"groupIndex":7},{"__type__":"cc.Label","node":{"__id__":12},"_useOriginalSize":false,"_string":"Label","_N$string":"Label","_fontSize":20,"_N$horizontalAlign":1,"_N$verticalAlign":1},{"__type__":"cc.Node","_name":"Left Menu","_parent":{"__id__":9},"_children":[{"__id__":15}],"_components":[{"__type__":"cc.Widget","node":{"__id__":14},"_alignFlags":9,"_left":-23,"_top":-23}],"_prefab":{"__type__":"cc.PrefabInfo","root":{"__id__":14},"asset":{"__uuid__":"6ci1CbxR9HcJuwnERKv5yD"},"fileId":"f1ydjOcixPCqfRy24wZSRW"},"_trs":{"__type__":"TypedArray","ctor":"Float64Array","array":[-480,320,0,0,0,0,1,1,1,1]},"_groupIndex":7,"groupIndex":7},{"__type__":"cc.Node","_name":"btnBack","_parent":{"__id__":14},"_children":[{"__id__":16}],"_components":[{"__type__":"cc.Sprite","node":{"__id__":15},"_materials":[{"__uuid__":"ecpdLyjvZBwrvm+cedCcQy"}],"_spriteFrame":{"__uuid__":"a2MjXRFdtLlYQ5ouAFv/+R"},"_type":1,"_sizeMode":0},{"__id__":17}],"_prefab":{"__type__":"cc.PrefabInfo","root":{"__id__":14},"asset":{"__uuid__":"6ci1CbxR9HcJuwnERKv5yD"},"fileId":"715adW7LO1A/ZA67FJaVh1v"},"_color":{"__type__":"cc.Color","g":171,"b":248},"_contentSize":{"__type__":"cc.Size","width":141,"height":90},"_anchorPoint":{"__type__":"cc.Vec2","x":0.6976691438212628,"y":0.9695517305558904},"_trs":{"__type__":"TypedArray","ctor":"Float64Array","array":[0,0,0,0,0,0.3826834323650898,0.9238795325112867,1,1,1]},"_eulerAngles":{"__type__":"cc.Vec3","z":45},"_groupIndex":7,"groupIndex":7},{"__type__":"cc.Node","_name":"back icon","_parent":{"__id__":15},"_components":[{"__type__":"cc.Sprite","node":{"__id__":16},"_materials":[{"__uuid__":"ecpdLyjvZBwrvm+cedCcQy"}],"_srcBlendFactor":1,"_spriteFrame":{"__uuid__":"02GjIXRNdDj6if+Hv+vonZ"}}],"_prefab":{"__type__":"cc.PrefabInfo","root":{"__id__":14},"asset":{"__uuid__":"6ci1CbxR9HcJuwnERKv5yD"},"fileId":"8cZw5sGQdLVbn1tTdC1CUt"},"_contentSize":{"__type__":"cc.Size","width":24,"height":24},"_trs":{"__type__":"TypedArray","ctor":"Float64Array","array":[-4.392893314361572,-56.47005844116211,0,0,0,-0.3826834323650898,0.9238795325112867,1.7000000476837158,1.7000000476837158,1]},"_eulerAngles":{"__type__":"cc.Vec3","z":-45},"_groupIndex":7,"groupIndex":7},{"__type__":"cc.Button","node":{"__id__":15},"clickEvents":[{"__type__":"cc.ClickEvent","target":{"__id__":9},"_componentId":"04525pyYBlN26SWawaUF3dA","handler":"backToList"}],"_N$transition":1,"transition":1,"_N$normalColor":{"__type__":"cc.Color","g":171,"b":248},"_N$pressedColor":{"__type__":"cc.Color","g":141,"b":206},"pressedColor":{"__type__":"cc.Color","g":141,"b":206},"_N$hoverColor":{"__type__":"cc.Color","r":60,"g":186,"b":247},"hoverColor":{"__type__":"cc.Color","r":60,"g":186,"b":247},"_N$disabledColor":{"__type__":"cc.Color","r":255,"g":255,"b":255},"_N$target":{"__id__":15}},{"__type__":"cc.Node","_name":"Center Menu","_parent":{"__id__":9},"_children":[{"__id__":19},{"__id__":20}],"_components":[{"__type__":"cc.Widget","node":{"__id__":18},"_alignFlags":45,"_left":475,"_right":439,"_top":600,"_horizontalCenter":18}],"_prefab":{"__type__":"cc.PrefabInfo","root":{"__id__":18},"asset":{"__uuid__":"98Geqpg5RDwrIsjuR985Yq"},"fileId":"612uCk0ntIFZeVwJb0ciY5"},"_contentSize":{"__type__":"cc.Size","height":-4.61538478467592},"_trs":{"__type__":"TypedArray","ctor":"Float64Array","array":[18,-300,0,0,0,0,1,1.2999999523162842,1.2999999523162842,1]},"_groupIndex":7,"groupIndex":7},{"__type__":"cc.Node","_name":"next_scene","_parent":{"__id__":18},"_components":[{"__type__":"cc.Sprite","node":{"__id__":19},"_materials":[{"__uuid__":"ecpdLyjvZBwrvm+cedCcQy"}],"_srcBlendFactor":1,"_spriteFrame":{"__uuid__":"28tsJhakVPrYWSz2g4Kmv5"}},{"__type__":"cc.Button","node":{"__id__":19},"clickEvents":[{"__type__":"cc.ClickEvent","target":{"__id__":9},"_componentId":"04525pyYBlN26SWawaUF3dA","handler":"nextScene"}],"_N$transition":1,"transition":1,"_N$normalColor":{"__type__":"cc.Color","r":214,"g":214,"b":214},"_N$target":{"__id__":19}},{"__type__":"cc.Widget","node":{"__id__":19},"_alignFlags":32,"_right":-345.4000005722046}],"_prefab":{"__type__":"cc.PrefabInfo","root":{"__id__":18},"asset":{"__uuid__":"98Geqpg5RDwrIsjuR985Yq"},"fileId":"79eAfRmbxE6qvp2/Qe1g2B"},"_color":{"__type__":"cc.Color","r":214,"g":214,"b":214},"_contentSize":{"__type__":"cc.Size","width":24,"height":24},"_trs":{"__type__":"TypedArray","ctor":"Float64Array","array":[325,230,0,0,0,0,1,1.7000000476837158,1.7000000476837158,1]},"_groupIndex":7,"groupIndex":7},{"__type__":"cc.Node","_name":"prev_scene","_parent":{"__id__":18},"_components":[{"__type__":"cc.Sprite","node":{"__id__":20},"_materials":[{"__uuid__":"ecpdLyjvZBwrvm+cedCcQy"}],"_srcBlendFactor":1,"_spriteFrame":{"__uuid__":"f1pAvsFlJJtpAm0alGZ09+"}},{"__type__":"cc.Button","node":{"__id__":20},"clickEvents":[{"__type__":"cc.ClickEvent","target":{"__id__":9},"_componentId":"04525pyYBlN26SWawaUF3dA","handler":"prevScene"}],"_N$transition":1,"transition":1,"_N$normalColor":{"__type__":"cc.Color","r":214,"g":214,"b":214},"_N$target":{"__id__":20}},{"__type__":"cc.Widget","node":{"__id__":20},"_alignFlags":8,"_left":-375.4000005722046}],"_prefab":{"__type__":"cc.PrefabInfo","root":{"__id__":18},"asset":{"__uuid__":"98Geqpg5RDwrIsjuR985Yq"},"fileId":"60cjAvPQ9D15qIiwkFiCOS"},"_color":{"__type__":"cc.Color","r":214,"g":214,"b":214},"_contentSize":{"__type__":"cc.Size","width":24,"height":24},"_trs":{"__type__":"TypedArray","ctor":"Float64Array","array":[-355,230,0,0,0,0,1,1.7000000476837158,1.7000000476837158,1]},"_groupIndex":7,"groupIndex":7},{"__type__":"24cfdwVNiRAr45L2SE+u3Ib","node":{"__id__":22},"_material":{"__uuid__":"56bAEctMdB147dF/Mn0LEN"},"transitionTime":2},{"__type__":"cc.Node","_name":"transitions","_parent":{"__id__":1},"_components":[{"__id__":21}],"_trs":{"__type__":"TypedArray","ctor":"Float64Array","array":[0,0,0,0,0,0,1,1,1,1]},"_id":"43ICjv2YNJsoOrn2JraKF9"}],{"__type__":"cc.SpriteFrame","content":{"name":"prev_scene","texture":"68phLtPoZDwoiDU1vHcRr0","rect":[0,0,24,24],"offset":[0,0],"originalSize":[24,24],"capInsets":[0,0,0,0]}}]